[
  {
    "time_th": "2026-03-07 16:17:01",
    "mode": "product",
    "used_fallback": false,
    "post_id": "103528711426076_1514513727348153",
    "name": "ชุดสวิตช์ปลั๊ก เต้ารับ พร้อมหน้ากากรุ่นเมจิก Vena Meji series แบบขันน็อต",
    "link": "https://shopee.co.th/product/483492679/42302427786",
    "price": 36.0,
    "rating": 4.94,
    "sold": 27,
    "final_score": 210.96
  },
  {
    "time_th": "2026-03-07 16:51:15",
    "mode": "viral",
    "post_id": "103528711426076_1514533144012878",
    "used_fallback": false,
    "name": "",
    "link": "",
    "price": "",
    "rating": "",
    "sold": "",
    "final_score": ""
  }
]