{
  "ben": {
    "items": [
      "26780432142",
      "28269919958"
    ],
    "images": [
      "th-11134207-7ras8-m7z4oytxx4vief",
      "sg-11134201-7rfhv-m3gbm65qoq91c0"
    ],
    "titles": [
      "ตะขอติดผนัง ตะขอพลังช้าง แท้100% รับน้ำหนักได้ 20 kg ตะขอแขวน ตะขอ ที่ติดฝาผนัง ตะขอ ตะขอแขวนติดผนัง",
      "ฟิวส์ขนาดมินิ Mini Fuse  จัดเซทกล่อง 120ชิ้น พร้อมคีมดึงฟิวส์"
    ],
    "reels": []
  },
  "smart": {
    "items": [
      "26141111005",
      "25414214657"
    ],
    "images": [
      "th-11134207-81ztj-mer4kr1sv18l9d",
      "00f20e153c4ee318013b24053b669bbc"
    ],
    "titles": [
      "iFILM ฟิล์มกระจก กันรอย เลนส์กล้อง For iPhone 17 Pro Max 17Air 17Pro ฟิล์มกล้อง ไอโพน Ring Lens HD i",
      "Samsung Smart Watch Galaxy Fit3 สมาร์ทวอทช์ ระบบบลูทูธ 40mm (เลือกสีได้)"
    ],
    "reels": []
  }
}